LICENSE
README.md
pyproject.toml
setup.py
altrumai/__init__.py
altrumai/_client.py
altrumai/_models.py
altrumai.egg-info/PKG-INFO
altrumai.egg-info/SOURCES.txt
altrumai.egg-info/dependency_links.txt
altrumai.egg-info/requires.txt
altrumai.egg-info/top_level.txt