Metadata-Version: 2.1
Name: altrumai
Version: 1.1.2
Summary: A python client for interacting with AltrumAI APIs.
Home-page: UNKNOWN
Author: Yashwanth S
Author-email: yashwanth@aligne.ai
License: Apache-v2
Keywords: altrumai api client aligne
Platform: UNKNOWN
License-File: LICENSE
